dblink/__init__.py
dblink/base.py
dblink/exceptions.py
dblink-0.1.2.dist-info/DESCRIPTION.rst
dblink-0.1.2.dist-info/METADATA
dblink-0.1.2.dist-info/RECORD
dblink-0.1.2.dist-info/WHEEL
dblink-0.1.2.dist-info/metadata.json
dblink-0.1.2.dist-info/top_level.txt
