Metadata-Version: 2.0
Name: dblink
Version: 0.1.2
Summary: DBLink tools makes operation on exists table easier.
Home-page: https://github.com/skyduy/dblink
Author: skyduy
Author-email: cuteuy@gmail.com
License: MIT
Keywords: sql orm dblink
Platform: UNKNOWN
Classifier: Development Status :: 4 - Beta
Classifier: Intended Audience :: Developers
Classifier: Topic :: Software Development :: Build Tools
Classifier: License :: OSI Approved :: MIT License
Classifier: Programming Language :: Python :: 3.4
Classifier: Programming Language :: Python :: 3.5
Classifier: Programming Language :: Python :: 3.6
Requires-Dist: sqlalchemy (==1.2.2)
